Verilog/TrafficLightController/tlc.v
module tlc(ALRED, ALYELLOW, ALGREEN, BLRED, BLYELLOW, BLGREEN, Ta, Tb, RESET, CLK);
	parameter 
		width = 4,
		S0 = 3'b000,
		S1 = 3'b001,
		S2 = 3'b010,
		S3 = 3'b011,
		S4 = 3'b100,
		S5 = 3'b101;
	input Ta, Tb, RESET, CLK;
	output ALRED, ALYELLOW, ALGREEN, BLRED, BLYELLOW, BLGREEN; 
	reg [width - 1:0]state, nextstate;

	always @(posedge CLK, posedge RESET)
	begin
	if(RESET)
		state <= S0;
	else
		state <= nextstate;
	end
	
	//Next state logic:
	always @(state, Ta, Tb)
	case(state)
	S0:
		if(Ta == 1)
			nextstate <= S0;
		else
			nextstate <= S1;
	S1:
		nextstate <= S2;
	S2:
		nextstate <= S3;
	S3:
		if(Tb == 1)
			nextstate <= S3;
		else
			nextstate <= S4;
	S4:
		nextstate <= S5;
	S5:
		nextstate <= S0;
	default: nextstate <= S0;
	endcase

	//Output Logic:
	assign ALRED = (state == S3 || state == S4 || state == S5);
	assign ALYELLOW = (state == S1 || state == S2); 
	assign ALGREEN = (state ==  S0);
	assign BLRED = (state == S0 || state == S1 || state == S2);
	assign BLYELLOW = (state == S4 || state == S5);
	assign BLGREEN = (state == S3);

endmodule

Verilog/TrafficLightController/tlc_tb.v
`timescale 1ns/1ps
 
module testbench;

	reg Ta, Tb, RESET, CLK;
	wire ALRED, ALYELLOW, ALGREEN, BLRED, BLYELLOW, BLGREEN;

	tlc test(ALRED, ALYELLOW, ALGREEN, BLRED, BLYELLOW, BLGREEN, Ta, Tb, RESET, CLK);
	
	initial begin

	$dumpfile ("tlc_out.vcd"); 
	$dumpvars(0, testbench);
	
	CLK = 0;
	RESET = 1; Ta = 0; Tb = 0; $display("RESET = 1, State: S0->S0"); #10;
	RESET = 0; Ta = 1; Tb = 0; $display("Ta = 1, Tb = 0, State: S0"); #10;
	RESET = 0; Ta = 0; Tb = 0; $display("Ta = 0, Tb = 0, State: S1"); #10;
	RESET = 1; Ta = 0; Tb = 0; $display("RESET = 1, State: S1->S0"); #10;
	RESET = 0; Ta = 0; Tb = 1; $display("Ta = 0, Tb = 1, State: S1"); #10;
	RESET = 0; Ta = 0; Tb = 0; $display("Ta = 0, Tb = 0, State: S2"); #10;	
	RESET = 1; Ta = 0; Tb = 0; $display("RESET = 1, State: S2->S0"); #10;
	RESET = 0; Ta = 0; Tb = 0; $display("Ta = 1, Tb = 0, State: S1"); #10;
	RESET = 0; Ta = 1; Tb = 0; $display("Ta = 1, Tb = 0, State: S2"); #10;
	RESET = 0; Ta = 0; Tb = 0; $display("Ta = 0, Tb = 0, State: S3"); #10;
	RESET = 1; Ta = 0; Tb = 0; $display("RESET = 1, State: S3->S0"); #10;
	RESET = 0; Ta = 0; Tb = 0; $display("Ta = 0, Tb = 0, State: S1"); #10;
	RESET = 0; Ta = 1; Tb = 1; $display("Ta = 1, Tb = 1, State: S2"); #10;
	RESET = 0; Ta = 0; Tb = 1; $display("Ta = 0, Tb = 1, State: S3"); #10;
	RESET = 0; Ta = 0; Tb = 1; $display("Ta = 0, Tb = 1, State: S3"); #10;	
	RESET = 0; Ta = 0; Tb = 0; $display("Ta = 0, Tb = 0, State: S4"); #10;
	RESET = 1; Ta = 0; Tb = 0; $display("RESET = 1, STATE: S4->S0"); #10;
	RESET = 0; Ta = 0; Tb = 0; $display("Ta = 0, Tb = 0, State: S1"); #10;	
	RESET = 0; Ta = 1; Tb = 1; $display("Ta = 1, Tb = 1, State: S2");#10;
	RESET = 0; Ta = 1; Tb = 0; $display("Ta = 1, Tb = 0, State: S3"); #10;
	RESET = 0; Ta = 1; Tb = 0; $display("Ta = 1, Tb = 0, State: S4"); #10;
	RESET = 0; Ta = 0; Tb = 1; $display("Ta = 0, Tb = 1, State: S5"); #10;
	RESET = 1; Ta = 0; Tb = 0; $display("RESET = 1, STATE: S5->S0"); #10;
	RESET = 0; Ta = 0; Tb = 0; $display("Ta = 0, Tb = 0, State: S1"); #10;	
	RESET = 0; Ta = 1; Tb = 1; $display("Ta = 1, Tb = 1, State: S2"); #10;
	RESET = 0; Ta = 1; Tb = 1; $display("Ta = 1, Tb = 1, State: S3"); #10;
	RESET = 0; Ta = 1; Tb = 0; $display("Ta = 1, Tb = 0, State: S4"); #10;	
	RESET = 0; Ta = 1; Tb = 0; $display("Ta = 1, Tb = 0, State: S5"); #10;
	RESET = 0; Ta = 1; Tb = 1; $display("Ta = 1, Tb = 1, State: S0"); #10;
	RESET = 0; Ta = 0; Tb = 1; $display("Ta = 0, Tb = 1, State: S1"); #10;
	RESET = 0; Ta = 0; Tb = 0; $display("Ta = 0, Tb = 0, State: S2"); #10;
	RESET = 0; Ta = 0; Tb = 0; $display("Ta = 0, Tb = 0, State: S3"); #10;
	RESET = 0; Ta = 0; Tb = 0; $display("Ta = 0, Tb = 0, State: S4"); #10;
	RESET = 0; Ta = 1; Tb = 1; $display("Ta = 1, Tb = 1, State: S5"); #10;
	RESET = 0; Ta = 1; Tb = 1; $display("Ta = 1, Tb = 1, State: S0"); #10;
	$finish;
	end		

	always 
	#5 CLK = ~CLK;

endmodule

Verilog/TrafficLightController/tlc_out.vcd
$date
	Fri Jun  5 14:55:15 2020
$end
$version
	Icarus Verilog
$end
$timescale
	1ps
$end
$scope module testbench $end
$var wire 1 ! BLYELLOW $end
$var wire 1 " BLRED $end
$var wire 1 # BLGREEN $end
$var wire 1 $ ALYELLOW $end
$var wire 1 % ALRED $end
$var wire 1 & ALGREEN $end
$var reg 1 ' CLK $end
$var reg 1 ( RESET $end
$var reg 1 ) Ta $end
$var reg 1 * Tb $end
$scope module test $end
$var wire 1 % ALRED $end
$var wire 1 $ ALYELLOW $end
$var wire 1 " BLRED $end
$var wire 1 ! BLYELLOW $end
$var wire 1 ' CLK $end
$var wire 1 ( RESET $end
$var wire 1 ) Ta $end
$var wire 1 * Tb $end
$var wire 1 # BLGREEN $end
$var wire 1 & ALGREEN $end
$var reg 4 + nextstate [3:0] $end
$var reg 4 , state [3:0] $end
$upscope $end
$upscope $end
$enddefinitions $end
#0
$dumpvars
b0 ,
b1 +
0*
0)
1(
0'
1&
0%
0$
0#
1"
0!
$end
#5000
1'
#10000
b0 +
0'
1)
0(
#15000
1'
#20000
b1 +
0'
0)
#25000
b10 +
1$
0&
b1 ,
1'
#30000
b1 +
0$
1&
b0 ,
0'
1(
#35000
1'
#40000
0'
1*
0(
#45000
b10 +
1$
0&
b1 ,
1'
#50000
0'
0*
#55000
b11 +
b10 ,
1'
#60000
b1 +
0$
1"
1&
b0 ,
0'
1(
#65000
1'
#70000
0'
0(
#75000
b10 +
1$
0&
b1 ,
1'
#80000
0'
1)
#85000
b11 +
b10 ,
1'
#90000
0'
0)
#95000
b100 +
1%
0$
0"
1#
b11 ,
1'
#100000
b1 +
0%
1"
1&
0#
b0 ,
0'
1(
#105000
1'
#110000
0'
0(
#115000
b10 +
1$
0&
b1 ,
1'
#120000
0'
1*
1)
#125000
b11 +
b10 ,
1'
#130000
0'
0)
#135000
1%
0$
0"
1#
b11 ,
1'
#140000
0'
#145000
1'
#150000
b100 +
0'
0*
#155000
b101 +
1!
0#
b100 ,
1'
#160000
b1 +
0%
1"
0!
1&
b0 ,
0'
1(
#165000
1'
#170000
0'
0(
#175000
b10 +
1$
0&
b1 ,
1'
#180000
0'
1*
1)
#185000
b11 +
b10 ,
1'
#190000
0'
0*
#195000
b100 +
1%
0$
0"
1#
b11 ,
1'
#200000
0'
#205000
b101 +
1!
0#
b100 ,
1'
#210000
0'
1*
0)
#215000
b0 +
b101 ,
1'
#220000
b1 +
1"
0%
0!
1&
b0 ,
0'
0*
1(
#225000
1'
#230000
0'
0(
#235000
b10 +
1$
0&
b1 ,
1'
#240000
0'
1*
1)
#245000
b11 +
b10 ,
1'
#250000
0'
#255000
1%
0$
0"
1#
b11 ,
1'
#260000
b100 +
0'
0*
#265000
b101 +
1!
0#
b100 ,
1'
#270000
0'
#275000
b0 +
b101 ,
1'
#280000
0'
1*
#285000
1"
0%
0!
1&
b0 ,
1'
#290000
b1 +
0'
0)
#295000
b10 +
1$
0&
b1 ,
1'
#300000
0'
0*
#305000
b11 +
b10 ,
1'
#310000
0'
#315000
b100 +
1%
0$
0"
1#
b11 ,
1'
#320000
0'
#325000
b101 +
1!
0#
b100 ,
1'
#330000
0'
1*
1)
#335000
b0 +
b101 ,
1'
#340000
0'
#345000
1"
0%
0!
1&
b0 ,
1'
