Verilog/JohnsonCounter/counter.v
module dff(q,d,reset,clk);
output q;
input d,clk,reset;
reg q;

always@(posedge clk or reset)
begin
	if (reset==1) q=0;
	else q=d;
end
endmodule


module counter(q,reset,clk);
output [3:0]q;
input clk,reset;
wire w;

not n1 (w,q[3]);
dff f1(q[0],w,reset,clk);
dff f2(q[1],q[0],reset,clk);
dff f3(q[2],q[1],reset,clk);
dff f4(q[3],q[2],reset,clk);

endmodule

Verilog/JohnsonCounter/counter_tb.v
`timescale 10ns/1ps

module tb_johnson;
    // Inputs
    reg clock;
    reg r;
    // Outputs
    wire [3:0]Count_out;

counter uut (Count_out,r,clock); 

initial begin

$dumpfile ("counter.vcd"); 
$dumpvars(0,tb_johnson);

clock = 0;
r = 1;
#50 r=0;

end

always 
#3 clock=~clock;


initial begin
#300 $finish;
end

endmodule

Verilog/JohnsonCounter/counter.vcd
$date
	Fri Jun  5 14:45:52 2020
$end
$version
	Icarus Verilog
$end
$timescale
	1ps
$end
$scope module tb_johnson $end
$var wire 4 ! Count_out [3:0] $end
$var reg 1 " clock $end
$var reg 1 # r $end
$scope module uut $end
$var wire 1 " clk $end
$var wire 1 # reset $end
$var wire 1 $ w $end
$var wire 4 % q [3:0] $end
$scope module f1 $end
$var wire 1 " clk $end
$var wire 1 $ d $end
$var wire 1 # reset $end
$var reg 1 & q $end
$upscope $end
$scope module f2 $end
$var wire 1 " clk $end
$var wire 1 ' d $end
$var wire 1 # reset $end
$var reg 1 ( q $end
$upscope $end
$scope module f3 $end
$var wire 1 " clk $end
$var wire 1 ) d $end
$var wire 1 # reset $end
$var reg 1 * q $end
$upscope $end
$scope module f4 $end
$var wire 1 " clk $end
$var wire 1 + d $end
$var wire 1 # reset $end
$var reg 1 , q $end
$upscope $end
$upscope $end
$upscope $end
$enddefinitions $end
#0
$dumpvars
0,
0+
0*
0)
0(
0'
0&
b0 %
1$
1#
0"
b0 !
$end
#30000
1"
#60000
0"
#90000
1"
#120000
0"
#150000
1"
#180000
0"
#210000
1"
#240000
0"
#270000
1"
#300000
0"
#330000
1"
#360000
0"
#390000
1"
#420000
0"
#450000
1"
#480000
0"
#500000
1'
b1 !
b1 %
1&
0#
#510000
1)
b11 !
b11 %
1(
1"
#540000
0"
#570000
1+
b111 !
b111 %
1*
1"
#600000
0"
#630000
0$
b1111 !
b1111 %
1,
1"
#660000
0"
#690000
0'
b1110 !
b1110 %
0&
1"
#720000
0"
#750000
0)
b1100 !
b1100 %
0(
1"
#780000
0"
#810000
0+
b1000 !
b1000 %
0*
1"
#840000
0"
#870000
1$
b0 !
b0 %
0,
1"
#900000
0"
#930000
1'
b1 !
b1 %
1&
1"
#960000
0"
#990000
1)
b11 !
b11 %
1(
1"
#1020000
0"
#1050000
1+
b111 !
b111 %
1*
1"
#1080000
0"
#1110000
0$
b1111 !
b1111 %
1,
1"
#1140000
0"
#1170000
0'
b1110 !
b1110 %
0&
1"
#1200000
0"
#1230000
0)
b1100 !
b1100 %
0(
1"
#1260000
0"
#1290000
0+
b1000 !
b1000 %
0*
1"
#1320000
0"
#1350000
1$
b0 !
b0 %
0,
1"
#1380000
0"
#1410000
1'
b1 !
b1 %
1&
1"
#1440000
0"
#1470000
1)
b11 !
b11 %
1(
1"
#1500000
0"
#1530000
1+
b111 !
b111 %
1*
1"
#1560000
0"
#1590000
0$
b1111 !
b1111 %
1,
1"
#1620000
0"
#1650000
0'
b1110 !
b1110 %
0&
1"
#1680000
0"
#1710000
0)
b1100 !
b1100 %
0(
1"
#1740000
0"
#1770000
0+
b1000 !
b1000 %
0*
1"
#1800000
0"
#1830000
1$
b0 !
b0 %
0,
1"
#1860000
0"
#1890000
1'
b1 !
b1 %
1&
1"
#1920000
0"
#1950000
1)
b11 !
b11 %
1(
1"
#1980000
0"
#2010000
1+
b111 !
b111 %
1*
1"
#2040000
0"
#2070000
0$
b1111 !
b1111 %
1,
1"
#2100000
0"
#2130000
0'
b1110 !
b1110 %
0&
1"
#2160000
0"
#2190000
0)
b1100 !
b1100 %
0(
1"
#2220000
0"
#2250000
0+
b1000 !
b1000 %
0*
1"
#2280000
0"
#2310000
1$
b0 !
b0 %
0,
1"
#2340000
0"
#2370000
1'
b1 !
b1 %
1&
1"
#2400000
0"
#2430000
1)
b11 !
b11 %
1(
1"
#2460000
0"
#2490000
1+
b111 !
b111 %
1*
1"
#2520000
0"
#2550000
0$
b1111 !
b1111 %
1,
1"
#2580000
0"
#2610000
0'
b1110 !
b1110 %
0&
1"
#2640000
0"
#2670000
0)
b1100 !
b1100 %
0(
1"
#2700000
0"
#2730000
0+
b1000 !
b1000 %
0*
1"
#2760000
0"
#2790000
1$
b0 !
b0 %
0,
1"
#2820000
0"
#2850000
1'
b1 !
b1 %
1&
1"
#2880000
0"
#2910000
1)
b11 !
b11 %
1(
1"
#2940000
0"
#2970000
1+
b111 !
b111 %
1*
1"
