Verilog/mux4:1/4to1mux.v
/* 2to1 mux*/
module mux2 (in0, in1, select, out);

input in0,in1,select;  
output out;
wire s0,w0,w1; 

not n1 (s0, select);
and a1 (w0, s0, in0);
and a2 (w1, select, in1);
or g3	(out, w0, w1); 

endmodule

/* 4to1 mux */
module mux4 (out, a1, a2, b, in0, in1, in2, in3);

input a1, a2, b, in0, in1, in2, in3;
output out;
wire t1, t2;

mux2 m1 (in0, in1, a1, t1);
mux2 m2 (in2, in3, a2, t2);
mux2 m3 (t1, t2, b, out);

endmodule

Verilog/mux4:1/4to1mux_tb.v
`timescale 1ns/1ps

module tb_mux4;
	
	reg Din_i0;
	reg Din_i1;
	reg Din_i2;
	reg Din_i3;
	reg Din_a1;
	reg Din_a2;
	reg Din_b;
	wire Dof_out;

	mux4 test(Dof_out, Din_a1, Din_a2, Din_b, Din_i0, Din_i1, Din_i2, Din_i3);

	initial begin

	$dumpfile ("output_mux4.vcd"); 
	$dumpvars(0, tb_mux4);
	
	Din_i0 = 0; Din_i1 = 0; Din_i2 = 0; Din_i3 = 0; Din_a1 = 0; Din_a2 = 0; Din_b = 0; #10;
	Din_i0 = 0; Din_i1 = 0; Din_i2 = 0; Din_i3 = 0; Din_a1 = 0; Din_a2 = 0; Din_b = 1; #10;
	Din_i0 = 0; Din_i1 = 0; Din_i2 = 0; Din_i3 = 0; Din_a1 = 0; Din_a2 = 1; Din_b = 0; #10;
	Din_i0 = 0; Din_i1 = 0; Din_i2 = 0; Din_i3 = 0; Din_a1 = 0; Din_a2 = 1; Din_b = 1; #10;
	Din_i0 = 0; Din_i1 = 0; Din_i2 = 0; Din_i3 = 0; Din_a1 = 1; Din_a2 = 0; Din_b = 0; #10;
	Din_i0 = 0; Din_i1 = 0; Din_i2 = 0; Din_i3 = 0; Din_a1 = 1; Din_a2 = 0; Din_b = 1; #10;
	Din_i0 = 0; Din_i1 = 0; Din_i2 = 0; Din_i3 = 0; Din_a1 = 1; Din_a2 = 1; Din_b = 0; #10;
	Din_i0 = 0; Din_i1 = 0; Din_i2 = 0; Din_i3 = 0; Din_a1 = 1; Din_a2 = 1; Din_b = 1; #10;
	Din_i0 = 0; Din_i1 = 0; Din_i2 = 0; Din_i3 = 1; Din_a1 = 0; Din_a2 = 0; Din_b = 0; #10;
	Din_i0 = 0; Din_i1 = 0; Din_i2 = 0; Din_i3 = 1; Din_a1 = 0; Din_a2 = 0; Din_b = 1; #10;
	Din_i0 = 0; Din_i1 = 0; Din_i2 = 0; Din_i3 = 1; Din_a1 = 0; Din_a2 = 1; Din_b = 0; #10;
	Din_i0 = 0; Din_i1 = 0; Din_i2 = 0; Din_i3 = 1; Din_a1 = 0; Din_a2 = 1; Din_b = 1; #10;
	Din_i0 = 0; Din_i1 = 0; Din_i2 = 0; Din_i3 = 1; Din_a1 = 1; Din_a2 = 0; Din_b = 0; #10;
	Din_i0 = 0; Din_i1 = 0; Din_i2 = 0; Din_i3 = 1; Din_a1 = 1; Din_a2 = 0; Din_b = 1; #10;
	Din_i0 = 0; Din_i1 = 0; Din_i2 = 0; Din_i3 = 1; Din_a1 = 1; Din_a2 = 1; Din_b = 0; #10;
	Din_i0 = 0; Din_i1 = 0; Din_i2 = 0; Din_i3 = 1; Din_a1 = 1; Din_a2 = 1; Din_b = 1; #10;
	Din_i0 = 0; Din_i1 = 0; Din_i2 = 1; Din_i3 = 0; Din_a1 = 0; Din_a2 = 0; Din_b = 0; #10;
	Din_i0 = 0; Din_i1 = 0; Din_i2 = 1; Din_i3 = 0; Din_a1 = 0; Din_a2 = 0; Din_b = 1; #10;
	Din_i0 = 0; Din_i1 = 0; Din_i2 = 1; Din_i3 = 0; Din_a1 = 0; Din_a2 = 1; Din_b = 0; #10;
	Din_i0 = 0; Din_i1 = 0; Din_i2 = 1; Din_i3 = 0; Din_a1 = 0; Din_a2 = 1; Din_b = 1; #10;
	Din_i0 = 0; Din_i1 = 0; Din_i2 = 1; Din_i3 = 0; Din_a1 = 1; Din_a2 = 0; Din_b = 0; #10;
	Din_i0 = 0; Din_i1 = 0; Din_i2 = 1; Din_i3 = 0; Din_a1 = 1; Din_a2 = 0; Din_b = 1; #10;
	Din_i0 = 0; Din_i1 = 0; Din_i2 = 1; Din_i3 = 0; Din_a1 = 1; Din_a2 = 1; Din_b = 0; #10;
	Din_i0 = 0; Din_i1 = 0; Din_i2 = 1; Din_i3 = 0; Din_a1 = 1; Din_a2 = 1; Din_b = 1; #10;
	Din_i0 = 0; Din_i1 = 0; Din_i2 = 1; Din_i3 = 1; Din_a1 = 0; Din_a2 = 0; Din_b = 0; #10;
	Din_i0 = 0; Din_i1 = 0; Din_i2 = 1; Din_i3 = 1; Din_a1 = 0; Din_a2 = 0; Din_b = 1; #10;
	Din_i0 = 0; Din_i1 = 0; Din_i2 = 1; Din_i3 = 1; Din_a1 = 0; Din_a2 = 1; Din_b = 0; #10;
	Din_i0 = 0; Din_i1 = 0; Din_i2 = 1; Din_i3 = 1; Din_a1 = 0; Din_a2 = 1; Din_b = 1; #10;
	Din_i0 = 0; Din_i1 = 0; Din_i2 = 1; Din_i3 = 1; Din_a1 = 1; Din_a2 = 0; Din_b = 0; #10;
	Din_i0 = 0; Din_i1 = 0; Din_i2 = 1; Din_i3 = 1; Din_a1 = 1; Din_a2 = 0; Din_b = 1; #10;
	Din_i0 = 0; Din_i1 = 0; Din_i2 = 1; Din_i3 = 1; Din_a1 = 1; Din_a2 = 1; Din_b = 0; #10;
	Din_i0 = 0; Din_i1 = 0; Din_i2 = 1; Din_i3 = 1; Din_a1 = 1; Din_a2 = 1; Din_b = 1; #10;
	Din_i0 = 0; Din_i1 = 1; Din_i2 = 0; Din_i3 = 0; Din_a1 = 0; Din_a2 = 0; Din_b = 0; #10;
	Din_i0 = 0; Din_i1 = 1; Din_i2 = 0; Din_i3 = 0; Din_a1 = 0; Din_a2 = 0; Din_b = 1; #10;
	Din_i0 = 0; Din_i1 = 1; Din_i2 = 0; Din_i3 = 0; Din_a1 = 0; Din_a2 = 1; Din_b = 0; #10;
	Din_i0 = 0; Din_i1 = 1; Din_i2 = 0; Din_i3 = 0; Din_a1 = 0; Din_a2 = 1; Din_b = 1; #10;
	Din_i0 = 0; Din_i1 = 1; Din_i2 = 0; Din_i3 = 0; Din_a1 = 1; Din_a2 = 0; Din_b = 0; #10;
	Din_i0 = 0; Din_i1 = 1; Din_i2 = 0; Din_i3 = 0; Din_a1 = 1; Din_a2 = 0; Din_b = 1; #10;
	Din_i0 = 0; Din_i1 = 1; Din_i2 = 0; Din_i3 = 0; Din_a1 = 1; Din_a2 = 1; Din_b = 0; #10;
	Din_i0 = 0; Din_i1 = 1; Din_i2 = 0; Din_i3 = 0; Din_a1 = 1; Din_a2 = 1; Din_b = 1; #10;
	Din_i0 = 0; Din_i1 = 1; Din_i2 = 0; Din_i3 = 1; Din_a1 = 0; Din_a2 = 0; Din_b = 0; #10;
	Din_i0 = 0; Din_i1 = 1; Din_i2 = 0; Din_i3 = 1; Din_a1 = 0; Din_a2 = 0; Din_b = 1; #10;
	Din_i0 = 0; Din_i1 = 1; Din_i2 = 0; Din_i3 = 1; Din_a1 = 0; Din_a2 = 1; Din_b = 0; #10;
	Din_i0 = 0; Din_i1 = 1; Din_i2 = 0; Din_i3 = 1; Din_a1 = 0; Din_a2 = 1; Din_b = 1; #10;
	Din_i0 = 0; Din_i1 = 1; Din_i2 = 0; Din_i3 = 1; Din_a1 = 1; Din_a2 = 0; Din_b = 0; #10;
	Din_i0 = 0; Din_i1 = 1; Din_i2 = 0; Din_i3 = 1; Din_a1 = 1; Din_a2 = 0; Din_b = 1; #10;
	Din_i0 = 0; Din_i1 = 1; Din_i2 = 0; Din_i3 = 1; Din_a1 = 1; Din_a2 = 1; Din_b = 0; #10;
	Din_i0 = 0; Din_i1 = 1; Din_i2 = 0; Din_i3 = 1; Din_a1 = 1; Din_a2 = 1; Din_b = 1; #10;
	Din_i0 = 0; Din_i1 = 1; Din_i2 = 1; Din_i3 = 0; Din_a1 = 0; Din_a2 = 0; Din_b = 0; #10;
	Din_i0 = 0; Din_i1 = 1; Din_i2 = 1; Din_i3 = 0; Din_a1 = 0; Din_a2 = 0; Din_b = 1; #10;
	Din_i0 = 0; Din_i1 = 1; Din_i2 = 1; Din_i3 = 0; Din_a1 = 0; Din_a2 = 1; Din_b = 0; #10;
	Din_i0 = 0; Din_i1 = 1; Din_i2 = 1; Din_i3 = 0; Din_a1 = 0; Din_a2 = 1; Din_b = 1; #10;
	Din_i0 = 0; Din_i1 = 1; Din_i2 = 1; Din_i3 = 0; Din_a1 = 1; Din_a2 = 0; Din_b = 0; #10;
	Din_i0 = 0; Din_i1 = 1; Din_i2 = 1; Din_i3 = 0; Din_a1 = 1; Din_a2 = 0; Din_b = 1; #10;
	Din_i0 = 0; Din_i1 = 1; Din_i2 = 1; Din_i3 = 0; Din_a1 = 1; Din_a2 = 1; Din_b = 0; #10;
	Din_i0 = 0; Din_i1 = 1; Din_i2 = 1; Din_i3 = 0; Din_a1 = 1; Din_a2 = 1; Din_b = 1; #10;
	Din_i0 = 0; Din_i1 = 1; Din_i2 = 1; Din_i3 = 1; Din_a1 = 0; Din_a2 = 0; Din_b = 0; #10;
	Din_i0 = 0; Din_i1 = 1; Din_i2 = 1; Din_i3 = 1; Din_a1 = 0; Din_a2 = 0; Din_b = 1; #10;
	Din_i0 = 0; Din_i1 = 1; Din_i2 = 1; Din_i3 = 1; Din_a1 = 0; Din_a2 = 1; Din_b = 0; #10;
	Din_i0 = 0; Din_i1 = 1; Din_i2 = 1; Din_i3 = 1; Din_a1 = 0; Din_a2 = 1; Din_b = 1; #10;
	Din_i0 = 0; Din_i1 = 1; Din_i2 = 1; Din_i3 = 1; Din_a1 = 1; Din_a2 = 0; Din_b = 0; #10;
	Din_i0 = 0; Din_i1 = 1; Din_i2 = 1; Din_i3 = 1; Din_a1 = 1; Din_a2 = 0; Din_b = 1; #10;
	Din_i0 = 0; Din_i1 = 1; Din_i2 = 1; Din_i3 = 1; Din_a1 = 1; Din_a2 = 1; Din_b = 0; #10;
	Din_i0 = 0; Din_i1 = 1; Din_i2 = 1; Din_i3 = 1; Din_a1 = 1; Din_a2 = 1; Din_b = 1; #10;
	Din_i0 = 1; Din_i1 = 0; Din_i2 = 0; Din_i3 = 0; Din_a1 = 0; Din_a2 = 0; Din_b = 0; #10;
	Din_i0 = 1; Din_i1 = 0; Din_i2 = 0; Din_i3 = 0; Din_a1 = 0; Din_a2 = 0; Din_b = 1; #10;
	Din_i0 = 1; Din_i1 = 0; Din_i2 = 0; Din_i3 = 0; Din_a1 = 0; Din_a2 = 1; Din_b = 0; #10;
	Din_i0 = 1; Din_i1 = 0; Din_i2 = 0; Din_i3 = 0; Din_a1 = 0; Din_a2 = 1; Din_b = 1; #10;
	Din_i0 = 1; Din_i1 = 0; Din_i2 = 0; Din_i3 = 0; Din_a1 = 1; Din_a2 = 0; Din_b = 0; #10;
	Din_i0 = 1; Din_i1 = 0; Din_i2 = 0; Din_i3 = 0; Din_a1 = 1; Din_a2 = 0; Din_b = 1; #10;
	Din_i0 = 1; Din_i1 = 0; Din_i2 = 0; Din_i3 = 0; Din_a1 = 1; Din_a2 = 1; Din_b = 0; #10;
	Din_i0 = 1; Din_i1 = 0; Din_i2 = 0; Din_i3 = 0; Din_a1 = 1; Din_a2 = 1; Din_b = 1; #10;
	Din_i0 = 1; Din_i1 = 0; Din_i2 = 0; Din_i3 = 1; Din_a1 = 0; Din_a2 = 0; Din_b = 0; #10;
	Din_i0 = 1; Din_i1 = 0; Din_i2 = 0; Din_i3 = 1; Din_a1 = 0; Din_a2 = 0; Din_b = 1; #10;
	Din_i0 = 1; Din_i1 = 0; Din_i2 = 0; Din_i3 = 1; Din_a1 = 0; Din_a2 = 1; Din_b = 0; #10;
	Din_i0 = 1; Din_i1 = 0; Din_i2 = 0; Din_i3 = 1; Din_a1 = 0; Din_a2 = 1; Din_b = 1; #10;
	Din_i0 = 1; Din_i1 = 0; Din_i2 = 0; Din_i3 = 1; Din_a1 = 1; Din_a2 = 0; Din_b = 0; #10;
	Din_i0 = 1; Din_i1 = 0; Din_i2 = 0; Din_i3 = 1; Din_a1 = 1; Din_a2 = 0; Din_b = 1; #10;
	Din_i0 = 1; Din_i1 = 0; Din_i2 = 0; Din_i3 = 1; Din_a1 = 1; Din_a2 = 1; Din_b = 0; #10;
	Din_i0 = 1; Din_i1 = 0; Din_i2 = 0; Din_i3 = 1; Din_a1 = 1; Din_a2 = 1; Din_b = 1; #10;
	Din_i0 = 1; Din_i1 = 0; Din_i2 = 1; Din_i3 = 0; Din_a1 = 0; Din_a2 = 0; Din_b = 0; #10;
	Din_i0 = 1; Din_i1 = 0; Din_i2 = 1; Din_i3 = 0; Din_a1 = 0; Din_a2 = 0; Din_b = 1; #10;
	Din_i0 = 1; Din_i1 = 0; Din_i2 = 1; Din_i3 = 0; Din_a1 = 0; Din_a2 = 1; Din_b = 0; #10;
	Din_i0 = 1; Din_i1 = 0; Din_i2 = 1; Din_i3 = 0; Din_a1 = 0; Din_a2 = 1; Din_b = 1; #10;
	Din_i0 = 1; Din_i1 = 0; Din_i2 = 1; Din_i3 = 0; Din_a1 = 1; Din_a2 = 0; Din_b = 0; #10;
	Din_i0 = 1; Din_i1 = 0; Din_i2 = 1; Din_i3 = 0; Din_a1 = 1; Din_a2 = 0; Din_b = 1; #10;
	Din_i0 = 1; Din_i1 = 0; Din_i2 = 1; Din_i3 = 0; Din_a1 = 1; Din_a2 = 1; Din_b = 0; #10;
	Din_i0 = 1; Din_i1 = 0; Din_i2 = 1; Din_i3 = 0; Din_a1 = 1; Din_a2 = 1; Din_b = 1; #10;
	Din_i0 = 1; Din_i1 = 0; Din_i2 = 1; Din_i3 = 1; Din_a1 = 0; Din_a2 = 0; Din_b = 0; #10;
	Din_i0 = 1; Din_i1 = 0; Din_i2 = 1; Din_i3 = 1; Din_a1 = 0; Din_a2 = 0; Din_b = 1; #10;
	Din_i0 = 1; Din_i1 = 0; Din_i2 = 1; Din_i3 = 1; Din_a1 = 0; Din_a2 = 1; Din_b = 0; #10;
	Din_i0 = 1; Din_i1 = 0; Din_i2 = 1; Din_i3 = 1; Din_a1 = 0; Din_a2 = 1; Din_b = 1; #10;
	Din_i0 = 1; Din_i1 = 0; Din_i2 = 1; Din_i3 = 1; Din_a1 = 1; Din_a2 = 0; Din_b = 0; #10;
	Din_i0 = 1; Din_i1 = 0; Din_i2 = 1; Din_i3 = 1; Din_a1 = 1; Din_a2 = 0; Din_b = 1; #10;
	Din_i0 = 1; Din_i1 = 0; Din_i2 = 1; Din_i3 = 1; Din_a1 = 1; Din_a2 = 1; Din_b = 0; #10;
	Din_i0 = 1; Din_i1 = 0; Din_i2 = 1; Din_i3 = 1; Din_a1 = 1; Din_a2 = 1; Din_b = 1; #10;
	Din_i0 = 1; Din_i1 = 1; Din_i2 = 0; Din_i3 = 0; Din_a1 = 0; Din_a2 = 0; Din_b = 0; #10;
	Din_i0 = 1; Din_i1 = 1; Din_i2 = 0; Din_i3 = 0; Din_a1 = 0; Din_a2 = 0; Din_b = 1; #10;
	Din_i0 = 1; Din_i1 = 1; Din_i2 = 0; Din_i3 = 0; Din_a1 = 0; Din_a2 = 1; Din_b = 0; #10;
	Din_i0 = 1; Din_i1 = 1; Din_i2 = 0; Din_i3 = 0; Din_a1 = 0; Din_a2 = 1; Din_b = 1; #10;
	Din_i0 = 1; Din_i1 = 1; Din_i2 = 0; Din_i3 = 0; Din_a1 = 1; Din_a2 = 0; Din_b = 0; #10;
	Din_i0 = 1; Din_i1 = 1; Din_i2 = 0; Din_i3 = 0; Din_a1 = 1; Din_a2 = 0; Din_b = 1; #10;
	Din_i0 = 1; Din_i1 = 1; Din_i2 = 0; Din_i3 = 0; Din_a1 = 1; Din_a2 = 1; Din_b = 0; #10;
	Din_i0 = 1; Din_i1 = 1; Din_i2 = 0; Din_i3 = 0; Din_a1 = 1; Din_a2 = 1; Din_b = 1; #10;
	Din_i0 = 1; Din_i1 = 1; Din_i2 = 0; Din_i3 = 1; Din_a1 = 0; Din_a2 = 0; Din_b = 0; #10;
	Din_i0 = 1; Din_i1 = 1; Din_i2 = 0; Din_i3 = 1; Din_a1 = 0; Din_a2 = 0; Din_b = 1; #10;
	Din_i0 = 1; Din_i1 = 1; Din_i2 = 0; Din_i3 = 1; Din_a1 = 0; Din_a2 = 1; Din_b = 0; #10;
	Din_i0 = 1; Din_i1 = 1; Din_i2 = 0; Din_i3 = 1; Din_a1 = 0; Din_a2 = 1; Din_b = 1; #10;
	Din_i0 = 1; Din_i1 = 1; Din_i2 = 0; Din_i3 = 1; Din_a1 = 1; Din_a2 = 0; Din_b = 0; #10;
	Din_i0 = 1; Din_i1 = 1; Din_i2 = 0; Din_i3 = 1; Din_a1 = 1; Din_a2 = 0; Din_b = 1; #10;
	Din_i0 = 1; Din_i1 = 1; Din_i2 = 0; Din_i3 = 1; Din_a1 = 1; Din_a2 = 1; Din_b = 0; #10;
	Din_i0 = 1; Din_i1 = 1; Din_i2 = 0; Din_i3 = 1; Din_a1 = 1; Din_a2 = 1; Din_b = 1; #10;
	Din_i0 = 1; Din_i1 = 1; Din_i2 = 1; Din_i3 = 0; Din_a1 = 0; Din_a2 = 0; Din_b = 0; #10;
	Din_i0 = 1; Din_i1 = 1; Din_i2 = 1; Din_i3 = 0; Din_a1 = 0; Din_a2 = 0; Din_b = 1; #10;
	Din_i0 = 1; Din_i1 = 1; Din_i2 = 1; Din_i3 = 0; Din_a1 = 0; Din_a2 = 1; Din_b = 0; #10;
	Din_i0 = 1; Din_i1 = 1; Din_i2 = 1; Din_i3 = 0; Din_a1 = 0; Din_a2 = 1; Din_b = 1; #10;
	Din_i0 = 1; Din_i1 = 1; Din_i2 = 1; Din_i3 = 0; Din_a1 = 1; Din_a2 = 0; Din_b = 0; #10;
	Din_i0 = 1; Din_i1 = 1; Din_i2 = 1; Din_i3 = 0; Din_a1 = 1; Din_a2 = 0; Din_b = 1; #10;
	Din_i0 = 1; Din_i1 = 1; Din_i2 = 1; Din_i3 = 0; Din_a1 = 1; Din_a2 = 1; Din_b = 0; #10;
	Din_i0 = 1; Din_i1 = 1; Din_i2 = 1; Din_i3 = 0; Din_a1 = 1; Din_a2 = 1; Din_b = 1; #10;
	Din_i0 = 1; Din_i1 = 1; Din_i2 = 1; Din_i3 = 1; Din_a1 = 0; Din_a2 = 0; Din_b = 0; #10;
	Din_i0 = 1; Din_i1 = 1; Din_i2 = 1; Din_i3 = 1; Din_a1 = 0; Din_a2 = 0; Din_b = 1; #10;
	Din_i0 = 1; Din_i1 = 1; Din_i2 = 1; Din_i3 = 1; Din_a1 = 0; Din_a2 = 1; Din_b = 0; #10;
	Din_i0 = 1; Din_i1 = 1; Din_i2 = 1; Din_i3 = 1; Din_a1 = 0; Din_a2 = 1; Din_b = 1; #10;
	Din_i0 = 1; Din_i1 = 1; Din_i2 = 1; Din_i3 = 1; Din_a1 = 1; Din_a2 = 0; Din_b = 0; #10;
	Din_i0 = 1; Din_i1 = 1; Din_i2 = 1; Din_i3 = 1; Din_a1 = 1; Din_a2 = 0; Din_b = 1; #10;
	Din_i0 = 1; Din_i1 = 1; Din_i2 = 1; Din_i3 = 1; Din_a1 = 1; Din_a2 = 1; Din_b = 0; #10;
	Din_i0 = 1; Din_i1 = 1; Din_i2 = 1; Din_i3 = 1; Din_a1 = 1; Din_a2 = 1; Din_b = 1; #10;

	end
	endmodule

Verilog/mux4:1/output_mux4.vcd
$date
	Fri Jun  5 14:15:44 2020
$end
$version
	Icarus Verilog
$end
$timescale
	1ps
$end
$scope module tb_mux4 $end
$var wire 1 ! Dof_out $end
$var reg 1 " Din_a1 $end
$var reg 1 # Din_a2 $end
$var reg 1 $ Din_b $end
$var reg 1 % Din_i0 $end
$var reg 1 & Din_i1 $end
$var reg 1 ' Din_i2 $end
$var reg 1 ( Din_i3 $end
$scope module test $end
$var wire 1 " a1 $end
$var wire 1 # a2 $end
$var wire 1 $ b $end
$var wire 1 % in0 $end
$var wire 1 & in1 $end
$var wire 1 ' in2 $end
$var wire 1 ( in3 $end
$var wire 1 ) t2 $end
$var wire 1 * t1 $end
$var wire 1 ! out $end
$scope module m1 $end
$var wire 1 % in0 $end
$var wire 1 & in1 $end
$var wire 1 * out $end
$var wire 1 + s0 $end
$var wire 1 " select $end
$var wire 1 , w0 $end
$var wire 1 - w1 $end
$upscope $end
$scope module m2 $end
$var wire 1 ' in0 $end
$var wire 1 ( in1 $end
$var wire 1 ) out $end
$var wire 1 . s0 $end
$var wire 1 # select $end
$var wire 1 / w0 $end
$var wire 1 0 w1 $end
$upscope $end
$scope module m3 $end
$var wire 1 * in0 $end
$var wire 1 ) in1 $end
$var wire 1 ! out $end
$var wire 1 1 s0 $end
$var wire 1 $ select $end
$var wire 1 2 w0 $end
$var wire 1 3 w1 $end
$upscope $end
$upscope $end
$upscope $end
$enddefinitions $end
#0
$dumpvars
03
02
11
00
0/
1.
0-
0,
1+
0*
0)
0(
0'
0&
0%
0$
0#
0"
0!
$end
#10000
01
1$
#20000
11
0.
0$
1#
#30000
01
1$
#40000
11
1.
0+
0$
0#
1"
#50000
01
1$
#60000
11
0.
0$
1#
#70000
01
1$
#80000
11
1.
1+
0$
0#
0"
1(
#90000
01
1$
#100000
1)
11
0.
10
0$
1#
#110000
1!
01
13
1$
#120000
0!
0)
11
03
1.
00
0+
0$
0#
1"
#130000
01
1$
#140000
1)
11
0.
10
0$
1#
#150000
1!
01
13
1$
#160000
0!
1/
1)
11
03
1.
1+
00
0$
0#
0"
0(
1'
#170000
1!
01
13
1$
#180000
0)
0!
0/
11
03
0.
0$
1#
#190000
01
1$
#200000
1)
1/
11
1.
0+
0$
0#
1"
#210000
1!
01
13
1$
#220000
0)
0!
0/
11
03
0.
0$
1#
#230000
01
1$
#240000
1)
1/
11
1.
1+
0$
0#
0"
1(
#250000
1!
01
13
1$
#260000
0!
0/
11
03
0.
10
0$
1#
#270000
1!
01
13
1$
#280000
0!
1/
1)
11
03
1.
00
0+
0$
0#
1"
#290000
1!
01
13
1$
#300000
0!
0/
11
03
0.
10
0$
1#
#310000
1!
01
13
1$
#320000
0!
0)
11
03
1.
1+
00
0$
0#
0"
0(
0'
1&
#330000
01
1$
#340000
11
0.
0$
1#
#350000
01
1$
#360000
1!
12
1*
11
1.
0+
1-
0$
0#
1"
#370000
0!
02
01
1$
#380000
1!
12
11
0.
0$
1#
#390000
0!
02
01
1$
#400000
0*
11
1.
1+
0-
0$
0#
0"
1(
#410000
01
1$
#420000
1)
11
0.
10
0$
1#
#430000
1!
01
13
1$
#440000
12
1!
0)
1*
11
03
1.
00
0+
1-
0$
0#
1"
#450000
0!
02
01
1$
#460000
1!
12
1)
11
0.
10
0$
1#
#470000
02
01
13
1$
#480000
0!
1/
0*
1)
11
03
1.
1+
0-
00
0$
0#
0"
0(
1'
#490000
1!
01
13
1$
#500000
0)
0!
0/
11
03
0.
0$
1#
#510000
01
1$
#520000
1!
1)
12
1/
1*
11
1.
0+
1-
0$
0#
1"
#530000
02
01
13
1$
#540000
0)
12
1!
0/
11
03
0.
0$
1#
#550000
0!
02
01
1$
#560000
1)
1/
0*
11
1.
1+
0-
0$
0#
0"
1(
#570000
1!
01
13
1$
#580000
0!
0/
11
03
0.
10
0$
1#
#590000
1!
01
13
1$
#600000
12
1!
1/
1)
1*
11
03
1.
00
0+
1-
0$
0#
1"
#610000
02
01
13
1$
#620000
12
1!
0/
11
03
0.
10
0$
1#
#630000
02
01
13
1$
#640000
12
1!
1,
0)
1*
11
03
1.
1+
00
0-
0$
0#
0"
0(
0'
0&
1%
#650000
0!
02
01
1$
#660000
1!
12
11
0.
0$
1#
#670000
0!
02
01
1$
#680000
0!
0*
02
0,
11
1.
0+
0$
0#
1"
#690000
01
1$
#700000
11
0.
0$
1#
#710000
01
1$
#720000
1!
12
1*
1,
11
1.
1+
0$
0#
0"
1(
#730000
0!
02
01
1$
#740000
1!
12
1)
11
0.
10
0$
1#
#750000
02
01
13
1$
#760000
0*
02
0!
0)
0,
11
03
1.
00
0+
0$
0#
1"
#770000
01
1$
#780000
1)
11
0.
10
0$
1#
#790000
1!
01
13
1$
#800000
12
1*
1!
1/
1,
1)
11
03
1.
1+
00
0$
0#
0"
0(
1'
#810000
02
01
13
1$
#820000
0)
12
1!
0/
11
03
0.
0$
1#
#830000
0!
02
01
1$
#840000
0!
1)
0*
02
1/
0,
11
1.
0+
0$
0#
1"
#850000
1!
01
13
1$
#860000
0)
0!
0/
11
03
0.
0$
1#
#870000
01
1$
#880000
1!
12
1)
1*
1/
1,
11
1.
1+
0$
0#
0"
1(
#890000
02
01
13
1$
#900000
12
1!
0/
11
03
0.
10
0$
1#
#910000
02
01
13
1$
#920000
0*
02
0!
1/
1)
0,
11
03
1.
00
0+
0$
0#
1"
#930000
1!
01
13
1$
#940000
0!
0/
11
03
0.
10
0$
1#
#950000
1!
01
13
1$
#960000
12
1*
1!
1,
0)
11
03
1.
1+
00
0$
0#
0"
0(
0'
1&
#970000
0!
02
01
1$
#980000
1!
12
11
0.
0$
1#
#990000
0!
02
01
1$
#1000000
1!
12
0,
11
1.
0+
1-
0$
0#
1"
#1010000
0!
02
01
1$
#1020000
1!
12
11
0.
0$
1#
#1030000
0!
02
01
1$
#1040000
1!
12
1,
1*
11
1.
1+
0-
0$
0#
0"
1(
#1050000
0!
02
01
1$
#1060000
1!
12
1)
11
0.
10
0$
1#
#1070000
02
01
13
1$
#1080000
12
1!
0)
0,
11
03
1.
00
0+
1-
0$
0#
1"
#1090000
0!
02
01
1$
#1100000
1!
12
1)
11
0.
10
0$
1#
#1110000
02
01
13
1$
#1120000
12
1!
1/
1,
1*
1)
11
03
1.
1+
0-
00
0$
0#
0"
0(
1'
#1130000
02
01
13
1$
#1140000
0)
12
1!
0/
11
03
0.
0$
1#
#1150000
0!
02
01
1$
#1160000
1!
1)
12
1/
0,
11
1.
0+
1-
0$
0#
1"
#1170000
02
01
13
1$
#1180000
0)
12
1!
0/
11
03
0.
0$
1#
#1190000
0!
02
01
1$
#1200000
1!
12
1)
1/
1,
1*
11
1.
1+
0-
0$
0#
0"
1(
#1210000
02
01
13
1$
#1220000
12
1!
0/
11
03
0.
10
0$
1#
#1230000
02
01
13
1$
#1240000
12
1!
1/
1)
0,
11
03
1.
00
0+
1-
0$
0#
1"
#1250000
02
01
13
1$
#1260000
12
1!
0/
11
03
0.
10
0$
1#
#1270000
02
01
13
1$
