Verilog/FSM/fsm.v
module fsm(out, clock, reset, in);

	input clock, reset, in;
	output out;
	reg out;
	reg [1:0]state;

	always @(posedge clock, posedge reset)
	if(reset == 1) begin
		state <= 2'b00;
		out <= 0;
	end
	else begin
		if(in == 0) 
			state <= 2'b01;
		else
			state <= 2'b10;

		if(state == 2'b01 && in == 1)
			out <= 1;
		else if(state == 2'b10 && in == 0)
			out <= 1;
		else
			out <= 0;
	end

endmodule

Verilog/FSM/fsm_tb.v
`timescale 1ns/1ps

module tb_fsm;

	reg in, clock, reset;
	wire out;	

	fsm test(out, clock, reset, in);

	initial begin

	$dumpfile ("fsm_out.vcd"); 
	$dumpvars(0, tb_fsm);

	clock = 0; in = 0; reset = 1; #8; //A->B->reset
	in = 1; reset = 1; #10;		// A->C->reset
	in = 0; reset = 0; #10;		// A->B
	in = 0; reset = 0; #10;		// B->B
	in = 1; reset = 0; #10;		// B->C
	in = 1; reset = 0; #10;		// C->C
	in = 0; reset = 0; #10;		// C->B
	in = 0; reset = 1; #10;		// B->B->reset
	in = 0; reset = 0; #10;		// A->B
	in = 1; reset = 1; #10;		// B->C->reset
	in = 1; reset = 0; #10;		// A->C
	in = 0; reset = 1; #10;		// C->B->reset
	in = 1; reset = 0; #10;		// A->C
	in = 1; reset = 1; #10;		// C->C->reset
	$finish;
	end

	always
	#5 clock = ~clock;

endmodule

Verilog/FSM/fsm_out.vcd
$date
	Fri Jun  5 14:40:28 2020
$end
$version
	Icarus Verilog
$end
$timescale
	1ps
$end
$scope module tb_fsm $end
$var wire 1 ! out $end
$var reg 1 " clock $end
$var reg 1 # in $end
$var reg 1 $ reset $end
$scope module test $end
$var wire 1 " clock $end
$var wire 1 # in $end
$var wire 1 $ reset $end
$var reg 1 ! out $end
$var reg 2 % state [1:0] $end
$upscope $end
$upscope $end
$enddefinitions $end
#0
$dumpvars
b0 %
1$
0#
0"
0!
$end
#5000
1"
#8000
1#
#10000
0"
#15000
1"
#18000
0$
0#
#20000
0"
#25000
b1 %
1"
#30000
0"
#35000
1"
#38000
1#
#40000
0"
#45000
1!
b10 %
1"
#50000
0"
#55000
0!
1"
#58000
0#
#60000
0"
#65000
1!
b1 %
1"
#68000
0!
b0 %
1$
#70000
0"
#75000
1"
#78000
0$
#80000
0"
#85000
b1 %
1"
#88000
b0 %
1$
1#
#90000
0"
#95000
1"
#98000
0$
#100000
0"
#105000
b10 %
1"
#108000
b0 %
1$
0#
#110000
0"
#115000
1"
#118000
0$
1#
#120000
0"
#125000
b10 %
1"
#128000
b0 %
1$
