Verilog/mux2:1/mux2.v

module mux2 (in0, in1, select, out);

input in0,in1,select;  
output out;
wire s0,w0,w1; 

not n1 (s0, select);
and a1 (w0, s0, in0);
and a2 (w1, select, in1);
or g3	(out, w0, w1); 

endmodule

Verilog/mux2:1/mux2_tb.v
`timescale 1ns/1ps

module tb_mux;

    reg Data_in_0;
    reg Data_in_1;
    reg sel;

    wire Data_out;

    mux2 uut (
        .in0(Data_in_0), 
        .in1(Data_in_1), 
        .select(sel), 
        .out(Data_out)
    );

    initial begin
	
	$dumpfile ("mux_out.vcd"); 
	$dumpvars(0, tb_mux);

        Data_in_0 = 0;
        Data_in_1 = 0;
        sel = 0;
 
        #100;
        
        Data_in_0 = 0;      Data_in_1 = 0;      sel = 1;      #10;
        Data_in_0 = 0;      Data_in_1 = 1;      sel = 0;      #10;
        Data_in_0 = 0;      Data_in_1 = 1;      sel = 1;      #10;
        Data_in_0 = 1;      Data_in_1 = 0;      sel = 0;      #50;
        Data_in_0 = 1;      Data_in_1 = 0;      sel = 1;      #10;
        Data_in_0 = 1;      Data_in_1 = 1;      sel = 0;      #10;
        Data_in_0 = 1;      Data_in_1 = 1;      sel = 1;      #10;
    end
      
endmodule

Verilog/mux2:1/mux_out.vcd
$date
	Fri Jun  5 14:10:15 2020
$end
$version
	Icarus Verilog
$end
$timescale
	1ps
$end
$scope module tb_mux $end
$var wire 1 ! Data_out $end
$var reg 1 " Data_in_0 $end
$var reg 1 # Data_in_1 $end
$var reg 1 $ sel $end
$scope module uut $end
$var wire 1 " in0 $end
$var wire 1 # in1 $end
$var wire 1 ! out $end
$var wire 1 % s0 $end
$var wire 1 $ select $end
$var wire 1 & w0 $end
$var wire 1 ' w1 $end
$upscope $end
$upscope $end
$enddefinitions $end
#0
$dumpvars
0'
0&
1%
0$
0#
0"
0!
$end
#100000
0%
1$
#110000
1%
0$
1#
#120000
1!
0%
1'
1$
#130000
1&
1!
1%
0'
0$
0#
1"
#180000
0!
0&
0%
1$
#190000
1!
1&
1%
0$
1#
#200000
0&
0%
1'
1$
